awarenessometer/__init__.py
awarenessometer/__main__.py
awarenessometer/data_preprocessor.py
awarenessometer/labeled_study.py
awarenessometer/plotter.py
awarenessometer/pre_post_study.py
awarenessometer/report_creator.py
awarenessometer/stats_helper.py
awarenessometer/locale/de_DE/LC_MESSAGES/plotter.mo
awarenessometer/templates/citsa_de_DE.md
awarenessometer/templates/citsa_en_US.md
awarenessometer/templates/iitsa_de_DE.md
awarenessometer/templates/iitsa_en_US.md
awarenessometer/templates/labeled_template_de_DE.md
awarenessometer/templates/labeled_template_en_US.md
awarenessometer/templates/pre_post_template_de_DE.md
awarenessometer/templates/pre_post_template_en_US.md
awarenessometer-2.0.0.dist-info/LICENSE
awarenessometer-2.0.0.dist-info/METADATA
awarenessometer-2.0.0.dist-info/WHEEL
awarenessometer-2.0.0.dist-info/entry_points.txt
awarenessometer-2.0.0.dist-info/top_level.txt
awarenessometer-2.0.0.dist-info/RECORD
