Metadata-Version: 2.1
Name: awarenessometer
Version: 2.0.0
Summary: Report generator for artifact-o-mat results
Home-page: https://gitlab.com/itsape/awarenssometer
Author: Timo Pohl, Arnold Sykosch
Maintainer: Arnold Sykosch
License: UNKNOWN
Platform: UNKNOWN
Classifier: Programming Language :: Python :: 3
Classifier: License :: OSI Approved :: MIT License
Classifier: Operating System :: OS Independent
Requires-Python: >=3.7
